sped_common/__init__.py
sped_common/arquivos.py
sped_common/blocos.py
sped_common/campos.py
sped_common/erros.py
sped_common/registros.py
sped_common-0.0.5.dist-info/DESCRIPTION.rst
sped_common-0.0.5.dist-info/METADATA
sped_common-0.0.5.dist-info/RECORD
sped_common-0.0.5.dist-info/WHEEL
sped_common-0.0.5.dist-info/metadata.json
sped_common-0.0.5.dist-info/top_level.txt
