Metadata-Version: 2.0
Name: sped-common
Version: 0.0.5
Summary: Biblioteca de componentes comuns do SPED.
Home-page: https://github.com/sped-br/python-sped-common
Author: Sergio Garcia
Author-email: sergio@ginx.com.br
License: MIT
Download-URL: https://github.com/sped-br/python-sped-common/releases
Keywords: sped fiscal contábil contabilidade receita federal
Platform: UNKNOWN
Classifier: Development Status :: 3 - Alpha
Classifier: Intended Audience :: Developers
Classifier: License :: OSI Approved :: MIT License
Classifier: Programming Language :: Python :: 3
Classifier: Programming Language :: Python :: 3.6
